prymes/__init__.py
prymes/_utils.py
prymes-0.0.1a1.dist-info/METADATA
prymes-0.0.1a1.dist-info/WHEEL
prymes-0.0.1a1.dist-info/licenses/LICENSE
prymes-0.0.1a1.dist-info/RECORD
