Metadata-Version: 2.3
Name: prymes
Version: 0.0.1a1
Summary: Python package for prime-related things
Author-email: Jingyang Wang <wangjy2010@126.com>
Maintainer-email: Jingyang Wang <wangjy2010@126.com>
License-File: LICENSE
Keywords: number-theory,primes
Classifier: Development Status :: 3 - Alpha
Classifier: License :: OSI Approved :: MIT License
Classifier: Operating System :: OS Independent
Classifier: Programming Language :: Python :: 3
Classifier: Programming Language :: Python :: 3.12
Requires-Python: >=3.12
